[{"Source": "python001/myclass.py/MyClass/print", "Target": "/home/user/.vscode/extensions/ms-python.vscode-pylance-2023.6.40/dist/typeshed-fallback/stdlib/builtins.pyi/print", "Type": "dependency"}, {"Source": "python001/myclass.py/MyClass/print", "Target": "/home/user/.vscode/extensions/ms-python.vscode-pylance-2023.6.40/dist/typeshed-fallback/stdlib/builtins.pyi/print", "Type": "dependency"}, {"Source": "python001/myclass.py/MyClass/print", "Target": "python001/myclass.py/MyClass/__init__", "Type": "dependency"}, {"Source": "python001/main.py", "Target": "/usr/lib/python3.11/re/__init__.py", "Type": "dependency"}, {"Source": "python001/main.py", "Target": "python001/myclass.py", "Type": "dependency"}, {"Source": "python001/main.py", "Target": "python001/myclass.py/MyClass", "Type": "dependency"}, {"Source": "python001/main.py/example_fun", "Target": "/home/user/.vscode/extensions/ms-python.vscode-pylance-2023.6.40/dist/typeshed-fallback/stdlib/builtins.pyi/str", "Type": "dependency"}, {"Source": "python001/main.py/example_fun/_get_regex", "Target": "/usr/lib/python3.11/re/__init__.py", "Type": "dependency"}, {"Source": "python001/main.py/example_fun/_get_regex", "Target": "/usr/lib/python3.11/re/__init__.py/compile", "Type": "dependency"}, {"Source": "python001/main.py/example_fun/_get_regex", "Target": "python001/main.py/example_fun", "Type": "dependency"}, {"Source": "python001/main.py/example_fun", "Target": "python001/main.py/example_fun/_get_regex", "Type": "dependency"}, {"Source": "python001/main.py/example_fun", "Target": "/usr/lib/python3.11/re/__init__.py", "Type": "dependency"}, {"Source": "python001/main.py/example_fun", "Target": "/usr/lib/python3.11/re/__init__.py/match", "Type": "dependency"}, {"Source": "python001/main.py/main", "Target": "python001/main.py/example_fun", "Type": "dependency"}, {"Source": "python001/main.py/main", "Target": "/home/user/.vscode/extensions/ms-python.vscode-pylance-2023.6.40/dist/typeshed-fallback/stdlib/builtins.pyi/print", "Type": "dependency"}, {"Source": "python001/main.py/main", "Target": "/home/user/.vscode/extensions/ms-python.vscode-pylance-2023.6.40/dist/typeshed-fallback/stdlib/builtins.pyi/print", "Type": "dependency"}, {"Source": "python001/main.py/main", "Target": "python001/myclass.py/MyClass", "Type": "dependency"}, {"Source": "python001/main.py/main", "Target": "python001/myclass.py/MyClass/print", "Type": "dependency"}, {"Source": "python001/main.py", "Target": "python001/main.py/main", "Type": "dependency"}]